sortd/__init__.py
sortd/__main__.py
sortd/consts.py
sortd/lib.py
sortd/py.typed
sortd/s_cfg.py
sortd/s_csv.py
sortd/s_json.py
sortd/s_lines.py
sortd/s_plist.py
sortd/s_toml.py
sortd/s_yaml.py
sortd-2.2.5.dist-info/METADATA
sortd-2.2.5.dist-info/WHEEL
sortd-2.2.5.dist-info/entry_points.txt
sortd-2.2.5.dist-info/top_level.txt
sortd-2.2.5.dist-info/RECORD
