Metadata-Version: 2.4
Name: sortd
Version: 2.2.5
Summary: sorting commands for stdin -> stdout
Author-email: ms-jpq <github@bigly.dog>
Project-URL: homepage, https://github.com/ms-jpq/sortd
Requires-Python: >=3.8.0
Requires-Dist: PyYAML
Requires-Dist: toml
Provides-Extra: dev
Requires-Dist: mypy; extra == "dev"
Requires-Dist: types-PyYAML; extra == "dev"
Requires-Dist: types-toml; extra == "dev"
Requires-Dist: isort; extra == "dev"
Requires-Dist: black; extra == "dev"
Provides-Extra: dist
Requires-Dist: wheel; extra == "dist"
